Workbook
Name ExpenseTable: Table2[#All]
Name IncomeTable: Income!$A$1:$I$121
Name Slicer_Category: #N/A
Name Slicer_Months__Date: #N/A
Name Slicer_Payment_Method: #N/A
Name Slicer_Vendor_Name: #N/A
Name VendorTable: Vendors!$A$1:$B$21

Sheet Dashboard
A1: Small Business Cash Flow & Expense Dashboard

Sheet About.
B4: Developed by: Jatin Singh
B5: Project Type: Microsoft Excel Dashboard Project
B6: Purpose: Portfolio Project – Data Analytics & Excel Freelancing
B7: Version: 1.0
B8: Completed: July 2026

Sheet Calculations
A1: Total income | B1: Total expense | C1: Net profit
A2: =SUM(Table1[Amount]) -> 130561 | B2: =SUM(Expenses!H:H) -> 127264 | C2: =A2-B2 -> 3297

Sheet Income
A1: Invoice No | B1: Date | C1: Customer | D1: Income Category | E1: Description | F1: Payment Method | G1: Amount | H1: Received By | I1: Remarks
A2: INV001 | B2: 46023 | C2: Modern Homes | D2: Service Income | E2: Consultation | F2: Cash | G2: 1017 | H2: Rohit | I2: Completed
A3: INV002 | B3: 46026 | C3: Royal Designers | D3: Service Income | E3: Delivery Charges | F3: Bank Transfer | G3: 1195 | H3: Jatin | I3: Cleared
A4: INV003 | B4: 46029 | C4: Sunrise Traders | D4: Interest | E4: Bank Interest | F4: Cash | G4: 86 | H4: Priya | I4: Completed
A5: INV004 | B5: 46032 | C5: Elegant Living | D5: Interest | E5: Bank Interest | F5: Debit Card | G5: 238 | H5: Rohit | I5: Verified
A6: INV005 | B6: 46035 | C6: Galaxy Furniture | D6: Sales | E6: MDF Boards | F6: Bank Transfer | G6: 2955 | H6: Jatin | I6: Cleared
A7: INV006 | B7: 46038 | C7: Build Masters | D7: Commission | E7: Sales Incentive | F7: Cheque | G7: 709 | H7: System | I7: Received
A8: INV007 | B8: 46041 | C8: Royal Furnishers | D8: Commission | E8: Referral Commission | F8: Cash | G8: 777 | H8: System | I8: Paid
A9: INV008 | B9: 46044 | C9: Sunrise Traders | D9: Commission | E9: Referral Commission | F9: Cash | G9: 570 | H9: Rohit | I9: Received
A10: INV009 | B10: 46047 | C10: Dream House | D10: Sales | E10: Decorative Panels | F10: UPI | G10: 3995 | H10: Jatin | I10: Paid
A11: INV010 | B11: 46050 | C11: City Decor | D11: Sales | E11: Laminates | F11: Bank Transfer | G11: 4583 | H11: Rohit | I11: Received
A12: INV011 | B12: 46053 | C12: Dream House | D12: Commission | E12: Dealer Commission | F12: UPI | G12: 445 | H12: Amit | I12: Cleared
A13: INV012 | B13: 46056 | C13: Galaxy Furniture | D13: Sales | E13: MDF Boards | F13: Credit Card | G13: 5004 | H13: System | I13: Verified
... A121: INV120 | B121: 46380 | C121: Dream Interiors | D121: Commission | E121: Referral Commission | F121: Credit Card | G121: 675 | H121: Rohit | I121: Completed

Sheet Expenses
A1: Expense ID | B1: Date | C1: Vendor Name | D1: Vendor ID | E1: Category | F1: Description | G1: Payment Method | H1: Amount | I1: Status | J1: Approved By | L1: Highest expense
A2: EXP001 | B2: 46024 | C2: City Electric | D2: =_xlfn.XLOOKUP(C2,Vendors!$B$2:$B$21,Vendors!$A$2:$A$21) -> V001 | E2: Software | F2: Microsoft 365 | G2: Credit Card | H2: 984 | I2: Pending | J2: Amit | L2: =MAX(Table2[Amount]) -> 4999
A3: EXP002 | B3: 46027 | C3: Courier Express | D3: =_xlfn.XLOOKUP(C3,Vendors!$B$2:$B$21,Vendors!$A$2:$A$21) -> V002 | E3: Fuel | F3: Petrol | G3: Debit Card | H3: 793 | I3: Pending | J3: Jatin
A4: EXP003 | B4: 46030 | C4: Prime Software | D4: =_xlfn.XLOOKUP(C4,Vendors!$B$2:$B$21,Vendors!$A$2:$A$21) -> V003 | E4: Miscellaneous | F4: Tea & Snacks | G4: Bank Transfer | H4: 600 | I4: Pending | J4: Priya
A5: EXP004 | B5: 46033 | C5: Repair Hub | D5: =_xlfn.XLOOKUP(C5,Vendors!$B$2:$B$21,Vendors!$A$2:$A$21) -> V004 | E5: Salary | F5: Sales Salary | G5: Cash | H5: 4999 | I5: Paid | J5: Manager
A6: EXP005 | B6: 46036 | C6: Office Depot | D6: =_xlfn.XLOOKUP(C6,Vendors!$B$2:$B$21,Vendors!$A$2:$A$21) -> V005 | E6: Packaging | F6: Boxes | G6: Cheque | H6: 873 | I6: Pending | J6: Amit
A7: EXP006 | B7: 46039 | C7: Power Company | D7: =_xlfn.XLOOKUP(C7,Vendors!$B$2:$B$21,Vendors!$A$2:$A$21) -> V006 | E7: Internet | F7: Broadband Bill | G7: Credit Card | H7: 502 | I7: Pending | J7: Manager
A8: EXP007 | B8: 46042 | C8: XYZ Logistics | D8: =_xlfn.XLOOKUP(C8,Vendors!$B$2:$B$21,Vendors!$A$2:$A$21) -> V007 | E8: Software | F8: CRM Subscription | G8: Cash | H8: 708 | I8: Paid | J8: Jatin
A9: EXP008 | B9: 46045 | C9: Secure Insurance | D9: =_xlfn.XLOOKUP(C9,Vendors!$B$2:$B$21,Vendors!$A$2:$A$21) -> V008 | E9: Internet | F9: Broadband Bill | G9: Debit Card | H9: 790 | I9: Pending | J9: Amit
A10: EXP009 | B10: 46048 | C10: Warehouse Supplies | D10: =_xlfn.XLOOKUP(C10,Vendors!$B$2:$B$21,Vendors!$A$2:$A$21) -> V009 | E10: Marketing | F10: Banner Printing | G10: Credit Card | H10: 788 | I10: Pending | J10: Amit
A11: EXP010 | B11: 46051 | C11: Power Company | D11: =_xlfn.XLOOKUP(C11,Vendors!$B$2:$B$21,Vendors!$A$2:$A$21) -> V006 | E11: Packaging | F11: Packing Tape | G11: Bank Transfer | H11: 537 | I11: Paid | J11: Jatin
A12: EXP011 | B12: 46054 | C12: CleanPro Services | D12: =_xlfn.XLOOKUP(C12,Vendors!$B$2:$B$21,Vendors!$A$2:$A$21) -> V010 | E12: Insurance | F12: Business Insurance | G12: Bank Transfer | H12: 191 | I12: Pending | J12: Amit
A13: EXP012 | B13: 46057 | C13: Repair Hub | D13: =_xlfn.XLOOKUP(C13,Vendors!$B$2:$B$21,Vendors!$A$2:$A$21) -> V004 | E13: Fuel | F13: Petrol | G13: Cash | H13: 454 | I13: Pending | J13: Manager
A14: EXP013 | B14: 46060 | C14: XYZ Logistics | D14: =_xlfn.XLOOKUP(C14,Vendors!$B$2:$B$21,Vendors!$A$2:$A$21) -> V007 | E14: Packaging | F14: Boxes | G14: Cash | H14: 1268 | I14: Paid | J14: Amit
... A121: EXP120 | B121: 46381 | C121: Prime Software | D121: =_xlfn.XLOOKUP(C121,Vendors!$B$2:$B$21,Vendors!$A$2:$A$21) -> V003 | E121: Miscellaneous | F121: Misc Expense | G121: Cash | H121: 573 | I121: Paid | J121: Priya

Sheet Cash Flow
A1: Date | B1: Cash In | C1: Cash Out | D1: Running Balance
A2: 46023 | B2: =SUMIFS(Income!$G$2:$G$121,Income!$B$2:$B$121,'Cash Flow'!A2) -> 1017 | C2: =SUMIFS(Expenses!$H$2:$H$121,Expenses!$B$2:$B$121,'Cash Flow'!A2) -> 0 | D2: =Settings!$C$6+B2-C2 -> 26017
A3: 46024 | B3: =SUMIFS(Income!$G$2:$G$121,Income!$B$2:$B$121,'Cash Flow'!A3) -> 0 | C3: =SUMIFS(Expenses!$H$2:$H$121,Expenses!$B$2:$B$121,'Cash Flow'!A3) -> 984 | D3: =D2+B3-C3 -> 25033 | F3: Expenses greater than $1,000 → Red fill.
A4: 46025 | B4: =SUMIFS(Income!$G$2:$G$121,Income!$B$2:$B$121,'Cash Flow'!A4) -> 0 | C4: =SUMIFS(Expenses!$H$2:$H$121,Expenses!$B$2:$B$121,'Cash Flow'!A4) -> 0 | D4: =D3+B4-C4 -> 25033 | F4: Pending payments → Yellow fill.
A5: 46026 | B5: =SUMIFS(Income!$G$2:$G$121,Income!$B$2:$B$121,'Cash Flow'!A5) -> 1195 | C5: =SUMIFS(Expenses!$H$2:$H$121,Expenses!$B$2:$B$121,'Cash Flow'!A5) -> 0 | D5: =D4+B5-C5 -> 26228 | F5: Income greater than $5,000 → Green fill.
A6: 46027 | B6: =SUMIFS(Income!$G$2:$G$121,Income!$B$2:$B$121,'Cash Flow'!A6) -> 0 | C6: =SUMIFS(Expenses!$H$2:$H$121,Expenses!$B$2:$B$121,'Cash Flow'!A6) -> 793 | D6: =D5+B6-C6 -> 25435
A7: 46028 | B7: =SUMIFS(Income!$G$2:$G$121,Income!$B$2:$B$121,'Cash Flow'!A7) -> 0 | C7: =SUMIFS(Expenses!$H$2:$H$121,Expenses!$B$2:$B$121,'Cash Flow'!A7) -> 0 | D7: =D6+B7-C7 -> 25435
A8: 46029 | B8: =SUMIFS(Income!$G$2:$G$121,Income!$B$2:$B$121,'Cash Flow'!A8) -> 86 | C8: =SUMIFS(Expenses!$H$2:$H$121,Expenses!$B$2:$B$121,'Cash Flow'!A8) -> 0 | D8: =D7+B8-C8 -> 25521
A9: 46030 | B9: =SUMIFS(Income!$G$2:$G$121,Income!$B$2:$B$121,'Cash Flow'!A9) -> 0 | C9: =SUMIFS(Expenses!$H$2:$H$121,Expenses!$B$2:$B$121,'Cash Flow'!A9) -> 600 | D9: =D8+B9-C9 -> 24921
A10: 46031 | B10: =SUMIFS(Income!$G$2:$G$121,Income!$B$2:$B$121,'Cash Flow'!A10) -> 0 | C10: =SUMIFS(Expenses!$H$2:$H$121,Expenses!$B$2:$B$121,'Cash Flow'!A10) -> 0 | D10: =D9+B10-C10 -> 24921
A11: 46032 | B11: =SUMIFS(Income!$G$2:$G$121,Income!$B$2:$B$121,'Cash Flow'!A11) -> 238 | C11: =SUMIFS(Expenses!$H$2:$H$121,Expenses!$B$2:$B$121,'Cash Flow'!A11) -> 0 | D11: =D10+B11-C11 -> 25159
A12: 46033 | B12: =SUMIFS(Income!$G$2:$G$121,Income!$B$2:$B$121,'Cash Flow'!A12) -> 0 | C12: =SUMIFS(Expenses!$H$2:$H$121,Expenses!$B$2:$B$121,'Cash Flow'!A12) -> 4999 | D12: =D11+B12-C12 -> 20160
A13: 46034 | B13: =SUMIFS(Income!$G$2:$G$121,Income!$B$2:$B$121,'Cash Flow'!A13) -> 0 | C13: =SUMIFS(Expenses!$H$2:$H$121,Expenses!$B$2:$B$121,'Cash Flow'!A13) -> 0 | D13: =D12+B13-C13 -> 20160
A14: 46035 | B14: =SUMIFS(Income!$G$2:$G$121,Income!$B$2:$B$121,'Cash Flow'!A14) -> 2955 | C14: =SUMIFS(Expenses!$H$2:$H$121,Expenses!$B$2:$B$121,'Cash Flow'!A14) -> 0 | D14: =D13+B14-C14 -> 23115
A15: 46036 | B15: =SUMIFS(Income!$G$2:$G$121,Income!$B$2:$B$121,'Cash Flow'!A15) -> 0 | C15: =SUMIFS(Expenses!$H$2:$H$121,Expenses!$B$2:$B$121,'Cash Flow'!A15) -> 873 | D15: =D14+B15-C15 -> 22242
A16: 46037 | B16: =SUMIFS(Income!$G$2:$G$121,Income!$B$2:$B$121,'Cash Flow'!A16) -> 0 | C16: =SUMIFS(Expenses!$H$2:$H$121,Expenses!$B$2:$B$121,'Cash Flow'!A16) -> 0 | D16: =D15+B16-C16 -> 22242
A17: 46038 | B17: =SUMIFS(Income!$G$2:$G$121,Income!$B$2:$B$121,'Cash Flow'!A17) -> 709 | C17: =SUMIFS(Expenses!$H$2:$H$121,Expenses!$B$2:$B$121,'Cash Flow'!A17) -> 0 | D17: =D16+B17-C17 -> 22951
... A366: 46387 | B366: =SUMIFS(Income!$G$2:$G$121,Income!$B$2:$B$121,'Cash Flow'!A366) -> 0 | C366: =SUMIFS(Expenses!$H$2:$H$121,Expenses!$B$2:$B$121,'Cash Flow'!A366) -> 0 | D366: =D365+B366-C366 -> 28297

Sheet Categories
A1: Commission | B1: Rent | C1: Cash | D1: Paid
A2: Income | B2: Expense | C2: Payment Methods | D2: Status
A3: Sales | B3: Rent | C3: Cash | D3: Paid
A4: Service Income | B4: Electricity | C4: Bank Transfer | D4: Pending
A5: Interest | B5: Internet | C5: Credit Card
A6: Commission | B6: Salary | C6: Debit Card
A7: Other Income | B7: Transportation | C7: UPI
B8: Fuel | C8: Cheque
B9: Office Supplies
B10: Marketing
B11: Packaging
B12: Software
B13: Tax
B14: Repair
B15: Insurance
B16: Miscellaneous

Sheet Vendors
A1: Vendor ID | B1: Vendor Name
A2: V001 | B2: City Electric
A3: V002 | B3: Courier Express
A4: V003 | B4: Prime Software
A5: V004 | B5: Repair Hub
A6: V005 | B6: Office Depot
A7: V006 | B7: Power Company
A8: V007 | B8: XYZ Logistics
A9: V008 | B9: Secure Insurance
A10: V009 | B10: Warehouse Supplies
A11: V010 | B11: CleanPro Services
A12: V011 | B12: Water Utility
... A21: V020 | B21: Furniture House

Sheet Settings
B2: Business Name | C2: ABC Trading Company
B3: Owner | C3: John Smith
B4: Currency | C4: USD
B5: Financial Year | C5: 2026
B6: Opening Balance | C6: 25000

Sheet Pivot Tables
A3: Months (Date) | B3: Income | D3: Months | E3: Expense | G3: Top Vendors | H3: Expense Amount | J3: Category | K3: Expense | M3: Payment Method | N3: Income
A4: Jan | B4: 238 | D4: Jan | E4: 1578 | G4: Secure Insurance | H4: 4032 | J4: Electricity | K4: 2777 | M4: Credit Card | N4: 13877
A5: Feb | B5: 10606 | D5: Feb | E5: 617 | G5: Repair Hub | H5: 2548 | J5: Fuel | K5: 454 | M5: Debit Card | N5: 1338
A6: Mar | B6: 4371 | D6: Mar | E6: 351 | G6: Warehouse Supplies | H6: 2508 | J6: Insurance | K6: 1894 | M6: Grand Total | N6: 15215
A7: Grand Total | B7: 15215 | D7: Apr | E7: 2308 | G7: Tax Office | H7: 1398 | J7: Internet | K7: 2014
D8: May | E8: 2651 | G8: Water Utility | H8: 1073 | J8: Marketing | K8: 5073
D9: Jun | E9: 573 | G9: XYZ Logistics | H9: 653 | J9: Grand Total | K9: 12212
D10: Aug | E10: 992 | G10: Grand Total | H10: 12212
D11: Oct | E11: 1783
D12: Nov | E12: 1359
D13: Grand Total | E13: 12212
